openapispecdiff/OpenApiSpecDiff.py
openapispecdiff/__init__.py
openapispecdiff-1.43.9.dist-info/LICENSE.txt
openapispecdiff-1.43.9.dist-info/METADATA
openapispecdiff-1.43.9.dist-info/WHEEL
openapispecdiff-1.43.9.dist-info/entry_points.txt
openapispecdiff-1.43.9.dist-info/top_level.txt
openapispecdiff-1.43.9.dist-info/RECORD
