Metadata-Version: 2.1
Name: openapispecdiff
Version: 1.43.9
Summary: Difference between two OpenAPISpec files
Author: Bala
Author-email: balak@cloudvector.com
Requires-Python: >=3.5,<4.0
License-File: LICENSE.txt
Requires-Dist: openapi-core (==0.13.4)
Requires-Dist: openapi-schema-validator (==0.1.1)
Requires-Dist: openapi-spec-validator (==0.2.9)
Requires-Dist: openapispecdiff
Requires-Dist: prance (==0.21.8.0)
